README.md
exception_handler.py
setup.cfg
setup.py
exception_handling_decorator.egg-info/PKG-INFO
exception_handling_decorator.egg-info/SOURCES.txt
exception_handling_decorator.egg-info/dependency_links.txt
exception_handling_decorator.egg-info/top_level.txt