Metadata-Version: 2.1
Name: exception-handling-decorator
Version: 0.1.7
Summary: ExceptionHandler: Python library to decorate        exception handling.
Home-page: https://github.com/bpzoran/exception-handling-decorator
Author: Zoran Jankovic
Author-email: bpzoran@yahoo.com
License: UNKNOWN
Platform: UNKNOWN
